m2metricforge/__init__.py
m2metricforge/main.py
m2metricforge-0.0.4.dist-info/LICENCE
m2metricforge-0.0.4.dist-info/METADATA
m2metricforge-0.0.4.dist-info/WHEEL
m2metricforge-0.0.4.dist-info/top_level.txt
m2metricforge-0.0.4.dist-info/RECORD
