Metadata-Version: 2.1
Name: m2metricforge
Version: 0.0.4
Summary: Library for generating validation dataset and evaluation metrics
Home-page: https://github.com/HDD-Team/metricforge
Author: m2syndicate
Author-email: mtwosyndicate@gmail.com
Project-URL: Documentation, https://github.com/HDD-Team/metricforge/blob/main/README.MD
Keywords: metric,validation,generate
Classifier: Programming Language :: Python :: 3.10
Classifier: License :: OSI Approved :: Apache Software License
Classifier: Operating System :: OS Independent
Requires-Python: >=3.7
License-File: LICENCE
Requires-Dist: langchain-core
Requires-Dist: langchain-community
Requires-Dist: pandas
Requires-Dist: scikit-learn
Requires-Dist: requests >=2.25.1
